openwisp_network_topology/__init__.py
openwisp_network_topology/admin.py
openwisp_network_topology/apps.py
openwisp_network_topology/consumers.py
openwisp_network_topology/contextmanagers.py
openwisp_network_topology/models.py
openwisp_network_topology/routing.py
openwisp_network_topology/settings.py
openwisp_network_topology/signals.py
openwisp_network_topology/tasks.py
openwisp_network_topology/urls.py
openwisp_network_topology/utils.py
openwisp_network_topology/api/__init__.py
openwisp_network_topology/api/filters.py
openwisp_network_topology/api/parsers.py
openwisp_network_topology/api/serializers.py
openwisp_network_topology/api/urls.py
openwisp_network_topology/api/views.py
openwisp_network_topology/base/__init__.py
openwisp_network_topology/base/link.py
openwisp_network_topology/base/node.py
openwisp_network_topology/base/snapshot.py
openwisp_network_topology/base/topology.py
openwisp_network_topology/fixtures/test_users.json
openwisp_network_topology/integrations/device/__init__.py
openwisp_network_topology/integrations/device/admin.py
openwisp_network_topology/integrations/device/apps.py
openwisp_network_topology/integrations/device/models.py
openwisp_network_topology/integrations/device/overrides.py
openwisp_network_topology/integrations/device/settings.py
openwisp_network_topology/integrations/device/tasks.py
openwisp_network_topology/integrations/device/base/__init__.py
openwisp_network_topology/integrations/device/base/models.py
openwisp_network_topology/integrations/device/management/commands/__init__.py
openwisp_network_topology/integrations/device/management/commands/create_device_nodes.py
openwisp_network_topology/integrations/device/migrations/0001_initial.py
openwisp_network_topology/integrations/device/migrations/0002_wifimesh.py
openwisp_network_topology/integrations/device/migrations/0003_wifimesh_permissions.py
openwisp_network_topology/integrations/device/migrations/__init__.py
openwisp_network_topology/integrations/device/tests/__init__.py
openwisp_network_topology-1.2.dist-info/licenses/LICENSE
openwisp_network_topology-1.2.dist-info/METADATA
openwisp_network_topology-1.2.dist-info/WHEEL
openwisp_network_topology-1.2.dist-info/top_level.txt
openwisp_network_topology-1.2.dist-info/RECORD
