Metadata-Version: 2.4
Name: openwisp-network-topology
Version: 1.2
Summary: OpenWISP Network Topology
Home-page: http://openwisp.org
Download-URL: https://github.com/openwisp/openwisp-network-topology/releases
Author: OpenWISP
Author-email: support@openwisp.io
License: BSD-3-Clause
Keywords: django,netjson,openwrt,networking,openwisp
Platform: Platform Independent
Classifier: Development Status :: 5 - Production/Stable
Classifier: Environment :: Web Environment
Classifier: Topic :: Internet :: WWW/HTTP
Classifier: Topic :: System :: Networking
Classifier: Intended Audience :: Developers
Classifier: License :: OSI Approved :: BSD License
Classifier: Operating System :: OS Independent
Classifier: Framework :: Django
Classifier: Programming Language :: Python :: 3
License-File: LICENSE
Requires-Dist: openwisp-users~=1.2.0
Requires-Dist: netdiff~=1.2.0
Requires-Dist: jsonfield~=3.1.0
Requires-Dist: django-flat-json-widget~=0.4.0
Requires-Dist: openwisp-utils[celery,channels]~=1.2.0
Dynamic: author
Dynamic: author-email
Dynamic: classifier
Dynamic: description
Dynamic: download-url
Dynamic: home-page
Dynamic: keywords
Dynamic: license
Dynamic: license-file
Dynamic: platform
Dynamic: requires-dist
Dynamic: summary
